MANIFEST.in
README.txt
license.txt
setup.py
Django_LocationBase.egg-info/PKG-INFO
Django_LocationBase.egg-info/SOURCES.txt
Django_LocationBase.egg-info/dependency_links.txt
Django_LocationBase.egg-info/not-zip-safe
Django_LocationBase.egg-info/requires.txt
Django_LocationBase.egg-info/top_level.txt
locationbase/__init__.py
locationbase/admin.py
locationbase/dist (1).py
locationbase/dist.py
locationbase/models.py
locationbase/tests.py
locationbase/urls.py
locationbase/views.py
locationbase/widgets.py
locationbase/static/css/location_picker.css
locationbase/static/js/location_picker.js
locationbase/templates/admin/locationbase/change_form.html
locationbase/templates/admin/locationbase/change_list.html
locationbase/templates/locationbase/location/geocoding.html
locationbase/templates/locationbase/location/list.html