Metadata-Version: 1.0
Name: Django-LocationBase
Version: 0.3.1
Summary: Reusable app for handling locations including longitude/latitude, location picking in admin and template tags for static map images.
Home-page: https://bitbucket.org/weholt/django-locationbase
Author: Thomas Weholt
Author-email: thomas@weholt.org
License: BSD
Keywords: longitude latitude altitude django location picking google maps integration
Platform: UNKNOWN
Classifier: Development Status :: 2 - Pre-Alpha
Classifier: Environment :: Web Environment
Classifier: Framework :: Django
Classifier: Intended Audience :: Developers
Classifier: License :: OSI Approved :: BSD License
Classifier: Operating System :: OS Independent
Classifier: Programming Language :: Python
Classifier: Topic :: Utilities
